arxiv/cloud_auth/domain.py
arxiv/cloud_auth/fastapi/auth.py
arxiv/cloud_auth/gcp_token_check.py
arxiv/cloud_auth/jwt.py
arxiv/cloud_auth/userstore.py
arxiv/cloud_auth/userstore_test_tables.py
arxiv_cloud_auth-0.1.2.dist-info/WHEEL
arxiv_cloud_auth-0.1.2.dist-info/METADATA
arxiv_cloud_auth-0.1.2.dist-info/RECORD
